{"results":{"1":{"definition":"hate","type":"","word":"Abhor"},"2":{"definition":"narrow-minded, prejudiced person","type":"","word":"Bigot"},"3":{"definition":"fake; false","type":"","word":"Counterfeit"},"4":{"definition":"give voting rights","type":"","word":"Enfranchise"},"5":{"definition":"hinder; obstruct","type":"","word":"Hamper"},"6":{"definition":"to start a fire","type":"","word":"Kindle"},"7":{"definition":"harmful; poisonous; lethal","type":"","word":"Noxious"},"8":{"definition":"calm; peaceful","type":"","word":"Placid"},"9":{"definition":"payment for work done","type":"","word":"Remuneration"},"10":{"definition":"lucky charm","type":"","word":"Talisman"},"11":{"definition":"rough; coarse; harsh","type":"","word":"Abrasive"},"12":{"definition":"cheat; defraud","type":"","word":"Bilk"},"13":{"definition":"hidden; undercover","type":"","word":"Covert"},"14":{"definition":"cause","type":"","word":"Engender"},"15":{"definition":"storage area (like garage) for a plane","type":"","word":"Hangar"},"16":{"definition":"complex; difficult to solve","type":"","word":"Knotty"},"17":{"definition":"something subtle; a fine shade of meaning","type":"","word":"Nuance"},"18":{"definition":"taking credit for someone else's writing or ideas","type":"","word":"Plagiarism"},"19":{"definition":"fame","type":"","word":"Renown"},"20":{"definition":"going off the main subject","type":"","word":"Tangent"},"21":{"definition":"humiliation; degradation","type":"","word":"Abasement"},"22":{"definition":"swelling; fluttering; waving","type":"","word":"Billowing"},"23":{"definition":"recoil in fear or servility; shrink away from","type":"","word":"Cower"},"24":{"definition":"improve; make better or clearer","type":"","word":"Enhance"},"25":{"definition":"noisy, attacking speech","type":"","word":"Harangue"},"26":{"definition":"a maze","type":"","word":"Labyrinth"},"27":{"definition":"to counter; make unimportant","type":"","word":"Nullify"},"28":{"definition":"petitioner (in court of law)","type":"","word":"Plaintiff"},"29":{"definition":"full","type":"","word":"Replete"},"30":{"definition":"can be touched","type":"","word":"Tangible"},"31":{"definition":"cancel; deny; repeal","type":"","word":"Abrogate"},"32":{"definition":"speech which offends religious sentiments","type":"","word":"Blasphemy"},"33":{"definition":"believable","type":"","word":"Credible"},"34":{"definition":"puzzle; mystery","type":"","word":"Enigma"},"35":{"definition":"indicators; bringers of warnings","type":"","word":"Harbingers"},"36":{"definition":"complicated; highly convoluted","type":"","word":"Labyrinthine"},"37":{"definition":"cuddle; snuggle","type":"","word":"Nuzzle"},"38":{"definition":"statement giving strong praise","type":"","word":"Plaudit"},"39":{"definition":"shameful; very bad","type":"","word":"Reprehensible"},"40":{"definition":"slow; late; overdue; delayed","type":"","word":"Tardy"},"41":{"definition":"forgiveness; pardon; release","type":"","word":"Absolution"},"42":{"definition":"obvious","type":"","word":"Blatant"},"43":{"definition":"praiseworthy","type":"","word":"Creditable"},"44":{"definition":"establish firmly in a position","type":"","word":"Ensconce"},"45":{"definition":"hurry; accelerate; rush","type":"","word":"Hasten"},"46":{"definition":"a cut","type":"","word":"Laceration"},"47":{"definition":"stubborn","type":"","word":"Obdurate"},"48":{"definition":"can be believed; reasonable","type":"","word":"Plausible"},"49":{"definition":"a respite; postponement of a sentence","type":"","word":"Reprieve"},"50":{"definition":"of little value; gaudy","type":"","word":"Tawdry"},"51":{"definition":"desist; go without; withdraw","type":"","word":"Abstain"},"52":{"definition":"damaged; destroyed; ruined","type":"","word":"Blighted"},"53":{"definition":"gullible; ready to believe anything","type":"","word":"Credulous"},"54":{"definition":"cover","type":"","word":"Enshroud"},"55":{"definition":"arrogance; pride","type":"","word":"Haughtiness"},"56":{"definition":"tearful; sad","type":"","word":"Lachrymose"},"57":{"definition":"deliberately make something difficult to understand","type":"","word":"Obfuscate"},"58":{"definition":"an excess","type":"","word":"Plethora"},"59":{"definition":"shun; eschew","type":"","word":"Repudiate"},"60":{"definition":"boredom","type":"","word":"Tedium"},"61":{"definition":"self denying; refraining from indulging","type":"","word":"Abstemious"},"62":{"definition":"free-spirited; carefree","type":"","word":"Blithe"},"63":{"definition":"active at dawn and dusk","type":"","word":"Crepuscular"},"64":{"definition":"clear pronunciation; accent; articulation","type":"","word":"Enunciation"},"65":{"definition":"stubborn; willful","type":"","word":"Headstrong"},"66":{"definition":"dull; monotonous; bland","type":"","word":"Lackluster"},"67":{"definition":"unbiased; not subjective","type":"","word":"Objective"},"68":{"definition":"flexible; not stubborn","type":"","word":"Pliable"},"69":{"definition":"retract; repeal","type":"","word":"Rescind"},"70":{"definition":"to moderate; soften","type":"","word":"Temper"},"71":{"definition":"difficult to understand; obscure","type":"","word":"Abstruse"},"72":{"definition":"1. ancient weapon (type of gun); 2. a clumsy person","type":"","word":"Blunderbuss"},"73":{"definition":"recoil; flinch; shy away","type":"","word":"Cringe"},"74":{"definition":"to cause bitterness and bad feeling","type":"","word":"Envenom"},"75":{"definition":"self indulgence; pleasure-seeking","type":"","word":"Hedonism"},"76":{"definition":"using few words; brief; to the point","type":"","word":"Laconic"},"77":{"definition":"indirect; slanting","type":"","word":"Oblique"},"78":{"definition":"feathers of a bird","type":"","word":"Plumage"},"79":{"definition":"acceptance of fate","type":"","word":"Resignation"},"80":{"definition":"stubborn; resolute; holding firm to a purpose","type":"","word":"Tenacious"},"81":{"definition":"tribute; honor; praise","type":"","word":"Accolade"},"82":{"definition":"support; prop up","type":"","word":"Bolster"},"83":{"definition":"puzzling; enigmatic","type":"","word":"Cryptic"},"84":{"definition":"short-lived","type":"","word":"Ephemeral"},"85":{"definition":"a pleasure seeker","type":"","word":"Hedonist"},"86":{"definition":"expression of regret or sorrow","type":"","word":"Lamentation"},"87":{"definition":"destroy; demolish; eradicate","type":"","word":"Obliterate"},"88":{"definition":"fall suddenly and steeply","type":"","word":"Plummet"},"89":{"definition":"determination","type":"","word":"Resolution"},"90":{"definition":"not certain","type":"","word":"Tentative"},"91":{"definition":"to agree to; give in to","type":"","word":"Acquiesce"},"92":{"definition":"arrogant, pompous language","type":"","word":"Bombast"},"93":{"definition":"cut short","type":"","word":"Curtail"},"94":{"definition":"someone who appreciates good food and drink","type":"","word":"Epicure"},"95":{"definition":"listen to","type":"","word":"Heed"},"96":{"definition":"ridicule; spoof","type":"","word":"Lampoon"},"97":{"definition":"totally unaware","type":"","word":"Oblivious"},"98":{"definition":"raised platform","type":"","word":"Podium"},"99":{"definition":"echoing","type":"","word":"Resonant"},"100":{"definition":"flimsy; not solid","type":"","word":"Tenuous"},"101":{"definition":"sharp; pungent (used of smells and tastes)","type":"","word":"Acrid"},"102":{"definition":"ill-mannered","type":"","word":"Boorish"},"103":{"definition":"believing that people act only out of selfish motives","type":"","word":"Cynical"},"104":{"definition":"a letter (form of communication)","type":"","word":"Epistle"},"105":{"definition":"against orthodox opinion","type":"","word":"Heresy"},"106":{"definition":"spear; spike; javelin","type":"","word":"Lance"},"107":{"definition":"difficult to understand; partially hidden","type":"","word":"Obscure"},"108":{"definition":"deeply moving; strongly affecting the emotions","type":"","word":"Poignant"},"109":{"definition":"a break; intermission","type":"","word":"Respite"},"110":{"definition":"concise; to the point","type":"","word":"Terse"},"111":{"definition":"fear of heights","type":"","word":"Acrophobia"},"112":{"definition":"middle class","type":"","word":"Bourgeois"},"113":{"definition":"weakness; incapacity","type":"","word":"Debility"},"114":{"definition":"concerned with letters; through correspondence","type":"","word":"Epistolary"},"115":{"definition":"interruption; pause","type":"","word":"Hiatus"},"116":{"definition":"tired; slow","type":"","word":"Languid"},"117":{"definition":"hidden; covered; buried","type":"","word":"Obscured"},"118":{"definition":"calm; collected; self-possessed","type":"","word":"Poised"},"119":{"definition":"shining; glowing","type":"","word":"Resplendent"},"120":{"definition":"medicinal; curative","type":"","word":"Therapeutic"},"121":{"definition":"sharpness (mental or visual)","type":"","word":"Acuity"},"122":{"definition":"someone who boasts","type":"","word":"Braggart"},"123":{"definition":"exposing false claims or myths","type":"","word":"Debunking"},"124":{"definition":"typified; characterized; personified","type":"","word":"Epitomized"},"125":{"definition":"rigid in opinions","type":"","word":"Hidebound"},"126":{"definition":"decay; fade away; get weaker","type":"","word":"Languish"},"127":{"definition":"servile; submissive","type":"","word":"Obsequious"},"128":{"definition":"causing debate or argument","type":"","word":"Polemical"},"129":{"definition":"a tonic","type":"","word":"Restorative"},"130":{"definition":"prevent; frustrate","type":"","word":"Thwart"},"131":{"definition":"forceful; inflexible","type":"","word":"Adamant"},"132":{"definition":"muscular","type":"","word":"Brawny"},"133":{"definition":"an athletic competition with ten events","type":"","word":"Decathlon"},"134":{"definition":"speak ambiguously; avoid telling the truth","type":"","word":"Equivocate"},"135":{"definition":"1. picture writing; 2. writing which is difficult to read or enigmatic","type":"","word":"Hieroglyphics"},"136":{"definition":"theft; robbery; stealing","type":"","word":"Larceny"},"137":{"definition":"a dominating concern","type":"","word":"Obsession"},"138":{"definition":"weighty; slow and heavy","type":"","word":"Ponderous"},"139":{"definition":"preservation; withholding","type":"","word":"Retention"},"140":{"definition":"cowardly; fearful","type":"","word":"Timorous"},"141":{"definition":"skilful \/ skillful","type":"","word":"Adroit"},"142":{"definition":"being brief","type":"","word":"Brevity"},"143":{"definition":"dignified, correct behavior [","type":"","word":"Decorum"},"144":{"definition":"]","type":"","word":"Err"},"145":{"definition":"make a mistake","type":"","word":"Hinder"},"146":{"definition":"obstruct","type":"","word":"Largess"},"147":{"definition":"generosity","type":"","word":"Obsolete"},"148":{"definition":"no longer valid","type":"","word":"Pontificate"},"149":{"definition":"speak pompously or dogmatically","type":"","word":"Reticent"},"150":{"definition":"restrained; holding something back; uncommunicative","type":"","word":"Tirade"},"151":{"definition":"stream of verbal abuse","type":"","word":"Adulation"},"152":{"definition":"strong admiration; worship","type":"","word":"Bristle"},"153":{"definition":"to show irritation","type":"","word":"Decoy"},"154":{"definition":"lure; trap; trick","type":"","word":"Erratic"},"155":{"definition":"wandering; irregular","type":"","word":"Histrionic"},"156":{"definition":"theatrical; exaggerated","type":"","word":"Laud"},"157":{"definition":"praise","type":"","word":"Obstreperous"},"158":{"definition":"noisy and boisterous","type":"","word":"Portend"},"159":{"definition":"foretell","type":"","word":"Retraction"},"160":{"definition":"withdrawal; cancellation of a statement","type":"","word":"Titter"},"161":{"definition":"giggle quietly","type":"","word":"Adversity"},"162":{"definition":"hardship","type":"","word":"Broach"},"163":{"definition":"start to discuss; approach","type":"","word":"Deference"},"164":{"definition":"respect","type":"","word":"Esoteric"},"165":{"definition":"obscure and difficult to understand","type":"","word":"Hoary"},"166":{"definition":"old","type":"","word":"Lavish"},"167":{"definition":"on a grand scale; wasteful","type":"","word":"Obtuse"},"168":{"definition":"mentally dull","type":"","word":"Portent"},"169":{"definition":"a warning sign; omen","type":"","word":"Revere"},"170":{"definition":"worship","type":"","word":"Tome"},"171":{"definition":"large book","type":"","word":"Advocate"},"172":{"definition":"support","type":"","word":"Brusque"},"173":{"definition":"blunt; abrupt","type":"","word":"Defoliate"},"174":{"definition":"cause leaves to fall off","type":"","word":"Espouse"},"175":{"definition":"promote; take up; support","type":"","word":"Hone"},"176":{"definition":"sharpen; increase; whet","type":"","word":"Lax"},"177":{"definition":"careless; not strict","type":"","word":"Obviate"},"178":{"definition":"avoid; make unnecessary","type":"","word":"Poseur"},"179":{"definition":"someone who puts on an act","type":"","word":"Riddled"},"180":{"definition":"full of (usually full of holes)","type":"","word":"Torpid"},"181":{"definition":"inactive; lazy; stagnant","type":"","word":"Aesthetic"},"182":{"definition":"concerning art or beauty","type":"","word":"Bulwark"},"183":{"definition":"fortification; barricade; wall","type":"","word":"Defunct"},"184":{"definition":"no longer in existence","type":"","word":"Etymology"},"185":{"definition":"the study of word origins","type":"","word":"Hyperbole"},"186":{"definition":"grossly exaggerated speech","type":"","word":"Legend"},"187":{"definition":"1. key to map;  2. myth or story","type":"","word":"Odious"},"188":{"definition":"hateful","type":"","word":"Posterity"},"189":{"definition":"future generations","type":"","word":"Rife"},"190":{"definition":"common","type":"","word":"Torpor"},"191":{"definition":"dormancy; sluggishness; inactivity","type":"","word":"Affable"},"192":{"definition":"friendly; social; easygoing","type":"","word":"Bureaucracy"},"193":{"definition":"officialdom","type":"","word":"Degradation"},"194":{"definition":"deprivation; poverty; debasement","type":"","word":"Eulogy"},"195":{"definition":"praise","type":"","word":"Hypochondriac"},"196":{"definition":"a person obsessed with health; having imaginary illnesses","type":"","word":"Legion"},"197":{"definition":"in large numbers","type":"","word":"Officious"},"198":{"definition":"domineering; intrusive; meddlesome","type":"","word":"Posthumous"},"199":{"definition":"after death","type":"","word":"Rigor"},"200":{"definition":"thoroughness","type":"","word":"Totter"},"201":{"definition":"eagerness; enthusiasm; quickness","type":"","word":"Alacrity"},"202":{"definition":"grow; flourish; put forth new shoots","type":"","word":"Burgeon"},"203":{"definition":"harmful","type":"","word":"Deleterious"},"204":{"definition":"a polite phrase to cover something unpleasant","type":"","word":"Euphemism"},"205":{"definition":"insincere","type":"","word":"Hypocritical"},"206":{"definition":"tired; without energy","type":"","word":"Lethargic"},"207":{"definition":"stare at; observe in an obvious manner","type":"","word":"Ogle"},"208":{"definition":"hypothesize; propose","type":"","word":"Postulate"},"209":{"definition":"strong; healthy; tough","type":"","word":"Robust"},"210":{"definition":"obedient; dutiful; polite","type":"","word":"Tractable"},"211":{"definition":"medieval chemistry; attempt to change base metal into gold","type":"","word":"Alchemy"},"212":{"definition":"polish","type":"","word":"Burnish"},"213":{"definition":"to think over deeply","type":"","word":"Deliberate"},"214":{"definition":"pleasant sounds","type":"","word":"Euphony"},"215":{"definition":"person who opposes orthodoxy","type":"","word":"Iconoclast"},"216":{"definition":"flippancy; joking about serious matters","type":"","word":"Levity"},"217":{"definition":"concerned with the sense of smell","type":"","word":"Olfactory"},"218":{"definition":"suitable for drinking","type":"","word":"Potable"},"219":{"definition":"round","type":"","word":"Rotund"},"220":{"definition":"peaceful","type":"","word":"Tranquil"},"221":{"definition":"an excuse that shows someone was not at a crime scene","type":"","word":"Alibi"},"222":{"definition":"strengthen; support","type":"","word":"Buttress"},"223":{"definition":"demarcation; explanation; definition; outlining","type":"","word":"Delineation"},"224":{"definition":"vacate; empty; abandon","type":"","word":"Evacuate"},"225":{"definition":"a personal peculiarity; something unique to an individual","type":"","word":"Idiosyncrasy"},"226":{"definition":"someone who opposes tyranny","type":"","word":"Libertarian"},"227":{"definition":"threatening","type":"","word":"Ominous"},"228":{"definition":"powerful; compelling; strong","type":"","word":"Potent"},"229":{"definition":"think over something; ponder","type":"","word":"Ruminate"},"230":{"definition":"copy","type":"","word":"Transcribe"},"231":{"definition":"to lessen","type":"","word":"Allay"},"232":{"definition":"the line that tells you who wrote an article","type":"","word":"Byline"},"233":{"definition":"hesitate; refuse","type":"","word":"Demur"},"234":{"definition":"make worse","type":"","word":"Exacerbate"},"235":{"definition":"shameful","type":"","word":"Ignominious"},"236":{"definition":"soothing lotion","type":"","word":"Liniment"},"237":{"definition":"all-powerful","type":"","word":"Omnipotent"},"238":{"definition":"practical","type":"","word":"Pragmatic"},"239":{"definition":"trick; stratagem","type":"","word":"Ruse"},"240":{"definition":"go astray; disobey; commit a sin","type":"","word":"Transgress"},"241":{"definition":"make less severe","type":"","word":"Alleviate"},"242":{"definition":"discordant loud noises","type":"","word":"Cacophony"},"243":{"definition":"condemn; speak out against","type":"","word":"Denounce"},"244":{"definition":"frustrated; annoyed","type":"","word":"Exasperated"},"245":{"definition":"shame [","type":"","word":"Ignominy"},"246":{"definition":"]","type":"","word":"Lithe"},"247":{"definition":"flexible; supple","type":"","word":"Omniscient"},"248":{"definition":"all-knowing","type":"","word":"Pragmatist"},"249":{"definition":"practical person; one who is concerned with usefulness","type":"","word":"Saccharin"},"250":{"definition":"falsely sweet","type":"","word":"Transient"},"251":{"definition":"short-lived; ephemeral","type":"","word":"Aloof"},"252":{"definition":"distant; detached; cold","type":"","word":"Cajole"},"253":{"definition":"coax","type":"","word":"Deplete"},"254":{"definition":"use up; lessen","type":"","word":"Exceptionable"},"255":{"definition":"very bad (something which we should object to)","type":"","word":"Illuminate"},"256":{"definition":"to light up or make clear","type":"","word":"Livid"},"257":{"definition":"very angry","type":"","word":"Onerous"},"258":{"definition":"burdensome; hard to undertake","type":"","word":"Preamble"},"259":{"definition":"introductory material","type":"","word":"Sacrosanct"},"260":{"definition":"very holy; inviolable","type":"","word":"Traverse"},"261":{"definition":"to move across","type":"","word":"Altruism"},"262":{"definition":"putting others first; being self-sacrificing","type":"","word":"Caldron"},"263":{"definition":"huge cooking pot","type":"","word":"Deplore"},"264":{"definition":"regret","type":"","word":"Exculpate"},"265":{"definition":"free someone from blame; pardon; acquit","type":"","word":"Illusory"},"266":{"definition":"deceptive; false; misleading","type":"","word":"Lobbyist"},"267":{"definition":"person who tries to persuade someone to support a particular cause","type":"","word":"Onus"},"268":{"definition":"burden","type":"","word":"Precarious"},"269":{"definition":"unstable; risky","type":"","word":"Sagacious"},"270":{"definition":"wise","type":"","word":"Trepidation"},"271":{"definition":"fear","type":"","word":"Amass"},"272":{"definition":"accumulate","type":"","word":"Callow"},"273":{"definition":"immature","type":"","word":"Depravity"},"274":{"definition":"moral corruption","type":"","word":"Execrable"},"275":{"definition":"very, very bad","type":"","word":"Immoderate"},"276":{"definition":"excessive; extreme","type":"","word":"Lofty"},"277":{"definition":"snooty; arrogant; haughty","type":"","word":"Opaque"},"278":{"definition":"does not let light through","type":"","word":"Precedent"},"279":{"definition":"a previous occurrence used as a guide","type":"","word":"Sage"},"280":{"definition":"a wise person","type":"","word":"Trinket"},"281":{"definition":"something of little value; knick-knack","type":"","word":"Ambiguity"},"282":{"definition":"uncertainty; vagueness","type":"","word":"Candid"},"283":{"definition":"frank; honest","type":"","word":"Deprecate"},"284":{"definition":"criticize; denounce","type":"","word":"Exegesis"},"285":{"definition":"scholarly explanation or interpretation","type":"","word":"Immutable"},"286":{"definition":"unchanging; permanent","type":"","word":"Longevity"},"287":{"definition":"long life","type":"","word":"Opulent"},"288":{"definition":"wealthy; rich; magnificent","type":"","word":"Precept"},"289":{"definition":"guiding principle","type":"","word":"Salacious"},"290":{"definition":"lecherous; erotic","type":"","word":"Trite"},"291":{"definition":"unoriginal; dull","type":"","word":"Ambiguous"},"292":{"definition":"unclear in meaning; can be interpreted in different ways","type":"","word":"Candor"},"293":{"definition":"frankness; openness","type":"","word":"Deride"},"294":{"definition":"ridicule; make fun of; mock","type":"","word":"Exemplary"},"295":{"definition":"outstandingly good; setting a fine example","type":"","word":"Impartial"},"296":{"definition":"unbiased; neutral","type":"","word":"Loquacious"},"297":{"definition":"talkative","type":"","word":"Ordain"},"298":{"definition":"1. destine; 2. confer holy orders on a priest","type":"","word":"Precinct"},"299":{"definition":"district of a city","type":"","word":"Sallow"},"300":{"definition":"yellowish","type":"","word":"Trivial"},"301":{"definition":"lack of clarity; wavering; being undecided","type":"","word":"Ambivalence"},"302":{"definition":"bad-tempered; quarrelsome","type":"","word":"Cantankerous"},"303":{"definition":"uncomplimentary","type":"","word":"Derogatory"},"304":{"definition":"to serve as a good example","type":"","word":"Exemplify"},"305":{"definition":"having no money","type":"","word":"Impecunious"},"306":{"definition":"clear","type":"","word":"Lucid"},"307":{"definition":"highly decorated","type":"","word":"Ornate"},"308":{"definition":"steep slope","type":"","word":"Precipice"},"309":{"definition":"health-giving","type":"","word":"Salubrious"},"310":{"definition":"shirker; someone absent without permission","type":"","word":"Truant"},"311":{"definition":"able to walk around (used of hospital patients)","type":"","word":"Ambulatory"},"312":{"definition":"spacious","type":"","word":"Capacious"},"313":{"definition":"to damage or pollute a holy place","type":"","word":"Desecrate"},"314":{"definition":"complete and thorough","type":"","word":"Exhaustive"},"315":{"definition":"wicked; profane","type":"","word":"Impious"},"316":{"definition":"ridiculous; silly","type":"","word":"Ludicrous"},"317":{"definition":"conventional","type":"","word":"Orthodox"},"318":{"definition":"done in a hurry","type":"","word":"Precipitous"},"319":{"definition":"something which teaches you a lesson; beneficial","type":"","word":"Salutary"},"320":{"definition":"cut short","type":"","word":"Truncate"},"321":{"definition":"make better","type":"","word":"Ameliorate"},"322":{"definition":"surrender; give in to","type":"","word":"Capitulate"},"323":{"definition":"spoiling something holy","type":"","word":"Desecration"},"324":{"definition":"acquits; absolves; removes blame","type":"","word":"Exonerates"},"325":{"definition":"destitute; poor","type":"","word":"Impoverished"},"326":{"definition":"1. unenthusiastic; 2. neither hot nor cold","type":"","word":"Lukewarm"},"327":{"definition":"1. turn to bone; 2. become fixed and rigid","type":"","word":"Ossify"},"328":{"definition":"prevent or make impossible","type":"","word":"Preclude"},"329":{"definition":"hypocritically holy","type":"","word":"Sanctimonious"},"330":{"definition":"uproar; noise","type":"","word":"Tumult"},"331":{"definition":"improvement","type":"","word":"Amelioration"},"332":{"definition":"constant criticism","type":"","word":"Carping"},"333":{"definition":"stop; discontinue; cease","type":"","word":"Desist"},"334":{"definition":"getting free\/rid of; eliminating (especially demons)","type":"","word":"Exorcism"},"335":{"definition":"unrehearsed; spontaneous","type":"","word":"Impromptu"},"336":{"definition":"clumsy person","type":"","word":"Lummox"},"337":{"definition":"showy","type":"","word":"Ostentatious"},"338":{"definition":"developing early","type":"","word":"Precocious"},"339":{"definition":"give approval to","type":"","word":"Sanction"},"340":{"definition":"depravity","type":"","word":"Turpitude"},"341":{"definition":"friendly","type":"","word":"Amiable"},"342":{"definition":"person who makes maps","type":"","word":"Cartographer"},"343":{"definition":"having no hope; miserable","type":"","word":"Despondent"},"344":{"definition":"refugee; emigrant; someone living away from his own country","type":"","word":"Expatriate"},"345":{"definition":"not intentional","type":"","word":"Inadvertent"},"346":{"definition":"juicy; moist; succulent","type":"","word":"Luscious"},"347":{"definition":"push out of a position","type":"","word":"Oust"},"348":{"definition":"one who came before","type":"","word":"Predecessor"},"349":{"definition":"bloodthirsty; bloody","type":"","word":"Sanguinary"},"350":{"definition":"novice; beginner","type":"","word":"Tyro"},"351":{"definition":"friendship","type":"","word":"Amity"},"352":{"definition":"scold strongly","type":"","word":"Castigate"},"353":{"definition":"hardship; poverty; misery","type":"","word":"Destitution"},"354":{"definition":"convenient; practical","type":"","word":"Expedient"},"355":{"definition":"chant; invocation; prayer","type":"","word":"Incantation"},"356":{"definition":"assassinate; kill; illegal hanging","type":"","word":"Lynch"},"357":{"definition":"obvious; not hidden","type":"","word":"Overt"},"358":{"definition":"dilemma; difficult situation","type":"","word":"Predicament"},"359":{"definition":"optimistic; cheerful","type":"","word":"Sanguine"},"360":{"definition":"found everywhere; omnipresent","type":"","word":"Ubiquitous"},"361":{"definition":"lacking in shape","type":"","word":"Amorphous"},"362":{"definition":"purging of pent-up emotions","type":"","word":"Catharsis"},"363":{"definition":"put off; prevent","type":"","word":"Deter"},"364":{"definition":"make faster","type":"","word":"Expedite"},"365":{"definition":"putting in prison","type":"","word":"Incarceration"},"366":{"definition":"plots and plans","type":"","word":"Machinations"},"367":{"definition":"worked up; in an emotional state","type":"","word":"Overwrought"},"368":{"definition":"famous; outstanding","type":"","word":"Preeminent"},"369":{"definition":"mocking","type":"","word":"Sardonic"},"370":{"definition":"undiluted; total","type":"","word":"Unalloyed"},"371":{"definition":"medicine to combat pain","type":"","word":"Analgesic"},"372":{"definition":"type of private political meeting","type":"","word":"Caucus"},"373":{"definition":"worsen; decline","type":"","word":"Deteriorate"},"374":{"definition":"clear explanation","type":"","word":"Exposition"},"375":{"definition":"without stopping","type":"","word":"Incessant"},"376":{"definition":"whirlpool; storm in the ocean","type":"","word":"Maelstrom"},"377":{"definition":"good to eat; agreeable","type":"","word":"Palatable"},"378":{"definition":"right or privilege","type":"","word":"Prerogative"},"379":{"definition":"person with knowledge","type":"","word":"Savant"},"380":{"definition":"oily; using excessive flattery","type":"","word":"Unctuous"},"381":{"definition":"comparable","type":"","word":"Analogous"},"382":{"definition":"burning","type":"","word":"Caustic"},"383":{"definition":"harmful","type":"","word":"Detrimental"},"384":{"definition":"praise","type":"","word":"Extol"},"385":{"definition":"just beginning","type":"","word":"Incipient"},"386":{"definition":"generous; big-hearted","type":"","word":"Magnanimous"},"387":{"definition":"fence made of posts","type":"","word":"Palisade"},"388":{"definition":"having fore-knowledge","type":"","word":"Prescient"},"389":{"definition":"to climb","type":"","word":"Scale"},"390":{"definition":"damaged; attacked","type":"","word":"Undermined"},"391":{"definition":"chaos; lack of government","type":"","word":"Anarchy"},"392":{"definition":"procession of vehicles","type":"","word":"Cavalcade"},"393":{"definition":"greedily eaten\/consumed","type":"","word":"Devoured"},"394":{"definition":"deport from one country back to the home country","type":"","word":"Extradite"},"395":{"definition":"tendency; a leaning toward","type":"","word":"Inclination"},"396":{"definition":"powerful businessman","type":"","word":"Magnate"},"397":{"definition":"a remedy that improves but doesn't cure","type":"","word":"Palliative"},"398":{"definition":"a feeling that something might happen","type":"","word":"Presentiment"},"399":{"definition":"person on whom blame is placed for faults of others","type":"","word":"Scapegoat"},"400":{"definition":"emphasize","type":"","word":"Underscore"},"401":{"definition":"a brief amusing story","type":"","word":"Anecdote"},"402":{"definition":"speed","type":"","word":"Celerity"},"403":{"definition":"skilful with hands","type":"","word":"Dexterous"},"404":{"definition":"irrelevant","type":"","word":"Extraneous"},"405":{"definition":"not clear","type":"","word":"Incoherent"},"406":{"definition":"clumsy; unskillful","type":"","word":"Maladroit"},"407":{"definition":"pale","type":"","word":"Pallid"},"408":{"definition":"assuming too much; arrogant","type":"","word":"Presumptuous"},"409":{"definition":"careful; diligent; painstaking","type":"","word":"Scrupulous"},"410":{"definition":"clear; obvious","type":"","word":"Unequivocal"},"411":{"definition":"hatred; antagonism","type":"","word":"Animosity"},"412":{"definition":"disapproving; critical","type":"","word":"Censorious"},"413":{"definition":"a division into two parts","type":"","word":"Dichotomy"},"414":{"definition":"extend; predict on the basis of known data","type":"","word":"Extrapolate"},"415":{"definition":"not fitting in; out of place","type":"","word":"Incongruous"},"416":{"definition":"illness","type":"","word":"Malady"},"417":{"definition":"easily felt; easily perceived","type":"","word":"Palpable"},"418":{"definition":"pompous; self-important","type":"","word":"Pretentious"},"419":{"definition":"examine carefully","type":"","word":"Scrutinize"},"420":{"definition":"set free","type":"","word":"Unfetter"},"421":{"definition":"a building which is an addition to an existing building","type":"","word":"Annex "},"422":{"definition":"blame","type":"","word":"Censure"},"423":{"definition":"intended to teach; instructive","type":"","word":"Didactic"},"424":{"definition":"irrelevant; on the outside","type":"","word":"Extrinsic"},"425":{"definition":"unimportant; insignificant; negligible","type":"","word":"Inconsequential"},"426":{"definition":"a curse","type":"","word":"Malediction"},"427":{"definition":"remedy for all ills","type":"","word":"Panacea"},"428":{"definition":"speak misleadingly and evasively","type":"","word":"Prevaricate"},"429":{"definition":"sink","type":"","word":"Scuttle"},"430":{"definition":"to remove a priest from his position","type":"","word":"Unfrock"},"431":{"definition":"take possession of; seize; capture","type":"","word":"Annex "},"432":{"definition":"intellectual","type":"","word":"Cerebral"},"433":{"definition":"lacking confidence","type":"","word":"Diffident"},"434":{"definition":"false","type":"","word":"Fallacious"},"435":{"definition":"not easily seen; subtle; not noticeable","type":"","word":"Inconspicuous"},"436":{"definition":"a wrong-doer","type":"","word":"Malefactor"},"437":{"definition":"1. example; 2. model; 3. way of looking at things","type":"","word":"Paradigm"},"438":{"definition":"unspoiled","type":"","word":"Pristine"},"439":{"definition":"an institution in which priests are trained","type":"","word":"Seminary"},"440":{"definition":"never having happened before","type":"","word":"Unprecedented"},"441":{"definition":"something which does not fit in a pattern; irregularity","type":"","word":"Anomaly"},"442":{"definition":"certainty","type":"","word":"Certitude"},"443":{"definition":"wander off the subject","type":"","word":"Digress"},"444":{"definition":"hesitate; waver","type":"","word":"Falter"},"445":{"definition":"cannot be wiped out","type":"","word":"Indelible"},"446":{"definition":"deliberately avoid work; shirk","type":"","word":"Malinger"},"447":{"definition":"apparently contradictory statement","type":"","word":"Paradox"},"448":{"definition":"tendency towards","type":"","word":"Proclivity"},"449":{"definition":"appealing to the senses","type":"","word":"Sensuous"},"450":{"definition":"unharmed; intact; without a scratch","type":"","word":"Unscathed"},"451":{"definition":"hostility; strong opposition","type":"","word":"Antagonism"},"452":{"definition":"trickster who claims knowledge he doesn't have","type":"","word":"Charlatan"},"453":{"definition":"dam; embankment","type":"","word":"Dike"},"454":{"definition":"obsessive; fixated","type":"","word":"Fanatical"},"455":{"definition":"1. neutral;  2. not outstanding","type":"","word":"Indifferent"},"456":{"definition":"person who deliberately tries to avoid work","type":"","word":"Malingerer"},"457":{"definition":"a perfect example","type":"","word":"Paragon"},"458":{"definition":"delay; put off","type":"","word":"Procrastinate"},"459":{"definition":"guard; sentry","type":"","word":"Sentinel"},"460":{"definition":"not deliberate; unconscious","type":"","word":"Unwitting"},"461":{"definition":"opposed; hostile; aggressive","type":"","word":"Antagonistic"},"462":{"definition":"wary of; cautious about; reluctant to give","type":"","word":"Chary"},"463":{"definition":"slow; falling behind with one's work","type":"","word":"Dilatory"},"464":{"definition":"passion; excessive devotion","type":"","word":"Fanaticism"},"465":{"definition":"native to a particular area","type":"","word":"Indigenous"},"466":{"definition":"flexible; can be shaped","type":"","word":"Malleable"},"467":{"definition":"of supreme importance","type":"","word":"Paramount"},"468":{"definition":"wasteful; extravagant","type":"","word":"Prodigal"},"469":{"definition":"isolate","type":"","word":"Sequester"},"470":{"definition":"scold; tell off; reprimand","type":"","word":"Upbraid"},"471":{"definition":"outdated; prehistoric; very old-fashioned","type":"","word":"Antediluvian"},"472":{"definition":"punishes","type":"","word":"Chastises"},"473":{"definition":"puzzling situation","type":"","word":"Dilemma"},"474":{"definition":"overly particular; finicky","type":"","word":"Fastidious"},"475":{"definition":"laziness","type":"","word":"Indolence"},"476":{"definition":"1. wooden hammer; 2. stick used for polo","type":"","word":"Mallet"},"477":{"definition":"1. scrounger; 2. animal which takes digested food from another","type":"","word":"Parasite"},"478":{"definition":"very large","type":"","word":"Prodigious"},"479":{"definition":"fortunate coincidence; unsought discovery","type":"","word":"Serendipity"},"480":{"definition":"hilarious; hysterical; very funny","type":"","word":"Uproarious"},"481":{"definition":"a book which is a collection of poems or stories","type":"","word":"Anthology"},"482":{"definition":"trickery","type":"","word":"Chicanery"},"483":{"definition":"person who dabbles in a subject without serious study","type":"","word":"Dilettante"},"484":{"definition":"silly; foolish","type":"","word":"Fatuous"},"485":{"definition":"novice; beginner","type":"","word":"Inductee"},"486":{"definition":"influencable; controllable","type":"","word":"Manipulatable"},"487":{"definition":"dried up","type":"","word":"Parched"},"488":{"definition":"unholy","type":"","word":"Profane"},"489":{"definition":"calm; peaceful","type":"","word":"Serene"},"490":{"definition":"outcome","type":"","word":"Upshot"},"491":{"definition":"putting man at the center of one's philosophy","type":"","word":"Anthropocentrism"},"492":{"definition":"changeable; unstable","type":"","word":"Chimerical"},"493":{"definition":"hard-working","type":"","word":"Diligent"},"494":{"definition":"possible and practicable","type":"","word":"Feasible"},"495":{"definition":"pampering; satisfying desires","type":"","word":"Indulgent"},"496":{"definition":"damaged; spoiled","type":"","word":"Marred"},"497":{"definition":"an outcast from society","type":"","word":"Pariah"},"498":{"definition":"swearing; cursing","type":"","word":"Profanity"},"499":{"definition":"jagged; saw-like","type":"","word":"Serrated"},"500":{"definition":"sophisticated; suave","type":"","word":"Urbane"},"501":{"definition":"outdated; old fashioned","type":"","word":"Antiquated"},"502":{"definition":"easily angered","type":"","word":"Choleric"},"503":{"definition":"model of a scene","type":"","word":"Diorama"},"504":{"definition":"fertile","type":"","word":"Fecund"},"505":{"definition":"drunkenness; intoxication","type":"","word":"Inebriation"},"506":{"definition":"to gather together","type":"","word":"Marshal"},"507":{"definition":"equality","type":"","word":"Parity"},"508":{"definition":"having deep meaning","type":"","word":"Profound"},"509":{"definition":"overly submissive; groveling","type":"","word":"Servile"},"510":{"definition":"take someone's position (usually by force)","type":"","word":"Usurp"},"511":{"definition":"indifferent; uninterested; lethargic","type":"","word":"Apathetic"},"512":{"definition":"person who records historical information","type":"","word":"Chronicler"},"513":{"definition":"mournful song","type":"","word":"Dirge"},"514":{"definition":"apt","type":"","word":"Felicitous"},"515":{"definition":"cannot be expressed in words","type":"","word":"Ineffable"},"516":{"definition":"pouched mammal (like a kangaroo)","type":"","word":"Marsupial"},"517":{"definition":"narrow-minded; concerned only with local matters","type":"","word":"Parochial"},"518":{"definition":"depth","type":"","word":"Profundity"},"519":{"definition":"doubting; not gullible","type":"","word":"Skeptical"},"520":{"definition":"useful","type":"","word":"Utilitarian"},"521":{"definition":"lack of interest or emotion","type":"","word":"Apathy"},"522":{"definition":"indirect","type":"","word":"Circuitous"},"523":{"definition":"disapproval","type":"","word":"Disapprobation"},"524":{"definition":"passion; enthusiasm","type":"","word":"Fervor"},"525":{"definition":"incompetent; unskilled; useless","type":"","word":"Inept"},"526":{"definition":"person who believes in strict discipline","type":"","word":"Martinet"},"527":{"definition":"a mockery; imitation for ridicule; spoof","type":"","word":"Parody"},"528":{"definition":"member of the working class","type":"","word":"Proletarian"},"529":{"definition":"minor battle","type":"","word":"Skirmish"},"530":{"definition":"a believer in an ideal world","type":"","word":"Utopian"},"531":{"definition":"of doubtful origin","type":"","word":"Apocryphal"},"532":{"definition":"using too many words; long-windedness","type":"","word":"Circumlocution"},"533":{"definition":"to distinguish one thing from another","type":"","word":"Discern"},"534":{"definition":"unpredictable; whimsical; easily swayed","type":"","word":"Fickle"},"535":{"definition":"inactivity; lethargy","type":"","word":"Inertia"},"536":{"definition":"person who intentionally inflicts pain on himself","type":"","word":"Masochist"},"537":{"definition":"ward off; avoid","type":"","word":"Parry"},"538":{"definition":"producing a lot","type":"","word":"Prolific"},"539":{"definition":"slow-moving; lethargic person","type":"","word":"Sluggard"},"540":{"definition":"waver; hesitate","type":"","word":"Vacillate"},"541":{"definition":"pacify; soothe; calm down; make peace with","type":"","word":"Appease"},"542":{"definition":"limit","type":"","word":"Circumscribe"},"543":{"definition":"disagreement","type":"","word":"Discord"},"544":{"definition":"skill","type":"","word":"Finesse"},"545":{"definition":"cannot be avoided","type":"","word":"Inevitable"},"546":{"definition":"society governed by women","type":"","word":"Matriarchy"},"547":{"definition":"economical; frugal; thrifty","type":"","word":"Parsimonious"},"548":{"definition":"promoters; supporters","type":"","word":"Proponents"},"549":{"definition":"refine an ore","type":"","word":"Smelt"},"550":{"definition":"empty; silly; meaningless","type":"","word":"Vacuous"},"551":{"definition":"worried; fearful","type":"","word":"Apprehensive"},"552":{"definition":"cautious; considering all sides","type":"","word":"Circumspect"},"553":{"definition":"cacophony; harshness; jarring","type":"","word":"Discordancy"},"554":{"definition":"not continuous; stopping and starting","type":"","word":"Fitful"},"555":{"definition":"relentless","type":"","word":"Inexorable"},"556":{"definition":"a loner","type":"","word":"Maverick"},"557":{"definition":"stinginess; frugality; cost-cutting","type":"","word":"Parsimony"},"558":{"definition":"dull; boring; ordinary","type":"","word":"Prosaic"},"559":{"definition":"a Swedish buffet of cold dishes","type":"","word":"Smorgasbord"},"560":{"definition":"person wandering without a home","type":"","word":"Vagrant"},"561":{"definition":"can be cultivated","type":"","word":"Arable"},"562":{"definition":"avoid","type":"","word":"Circumvent"},"563":{"definition":"something which does not match up; inconsistency","type":"","word":"Discrepancy"},"564":{"definition":"clearly wrong","type":"","word":"Flagrant"},"565":{"definition":"not advisable","type":"","word":"Inexpedient"},"566":{"definition":"in short supply","type":"","word":"Meager"},"567":{"definition":"biased; one-sided; committed to one group","type":"","word":"Partisan"},"568":{"definition":"forbid","type":"","word":"Proscribe"},"569":{"definition":"comfort for grief","type":"","word":"Solace"},"570":{"definition":"dull; uninspiring","type":"","word":"Vapid"},"571":{"definition":"random; for no definite reason","type":"","word":"Arbitrary"},"572":{"definition":"psychic; mystic","type":"","word":"Clairvoyant"},"573":{"definition":"to make a clear distinction; see the difference","type":"","word":"Discriminate"},"574":{"definition":"showy; ornate","type":"","word":"Flamboyant"},"575":{"definition":"perfect; flawless; cannot make mistakes","type":"","word":"Infallible"},"576":{"definition":"wander from side to side","type":"","word":"Meander"},"577":{"definition":"evoking sadness or pity","type":"","word":"Pathos"},"578":{"definition":"study of versification","type":"","word":"Prosody"},"579":{"definition":"to ask for; seek","type":"","word":"Solicit"},"580":{"definition":"multicolored; speckled","type":"","word":"Variegated"},"581":{"definition":"obscure; known only to a few people","type":"","word":"Arcane"},"582":{"definition":"shout; scream","type":"","word":"Clamor"},"583":{"definition":"long windedness; indirectness","type":"","word":"Discursiveness"},"584":{"definition":"show off; display in a showy manner","type":"","word":"Flaunt"},"585":{"definition":"famous for something bad","type":"","word":"Infamous"},"586":{"definition":"soft; melodious; ripe","type":"","word":"Mellow"},"587":{"definition":"one who give support (usually financial)","type":"","word":"Patron"},"588":{"definition":"1. lying face down; 2. be overcome with extreme weakness","type":"","word":"Prostration"},"589":{"definition":"sleepwalker","type":"","word":"Somnambulist"},"590":{"definition":"violence; fervor; forcefulness","type":"","word":"Vehemence"},"591":{"definition":"ancient; outdated; old fashioned","type":"","word":"Archaic"},"592":{"definition":"secret; covert; stealthy","type":"","word":"Clandestine"},"593":{"definition":"contempt; strong dislike","type":"","word":"Disdain"},"594":{"definition":"making jokes about serious matters","type":"","word":"Flippant"},"595":{"definition":"deduce; conclude","type":"","word":"Infer"},"596":{"definition":"collection of animals","type":"","word":"Menagerie"},"597":{"definition":"condescend to; behave in an arrogant manner towards","type":"","word":"Patronize"},"598":{"definition":"main character in film, book, play etc.","type":"","word":"Protagonist"},"599":{"definition":"fortuneteller","type":"","word":"Soothsayer"},"600":{"definition":"forceful","type":"","word":"Vehement"},"601":{"definition":"classic example of","type":"","word":"Archetype"},"602":{"definition":"mercy","type":"","word":"Clemency"},"603":{"definition":"unbiased","type":"","word":"Disinterested"},"604":{"definition":"defy; reject","type":"","word":"Flout"},"605":{"definition":"na\u00efve, unsophisticated person","type":"","word":"Ing\u00e9nue"},"606":{"definition":"given to lying","type":"","word":"Mendacious"},"607":{"definition":"shortage","type":"","word":"Paucity"},"608":{"definition":"changeable","type":"","word":"Protean"},"609":{"definition":"juvenile; immature","type":"","word":"Sophomoric"},"610":{"definition":"corrupt; can be bribed","type":"","word":"Venal"},"611":{"definition":"collections of old records; place of storage of old documents","type":"","word":"Archives"},"612":{"definition":"overused expression; something unoriginal","type":"","word":"Clich\u00e9"},"613":{"definition":"criticize; belittle","type":"","word":"Disparage"},"614":{"definition":"worked-up; not calm","type":"","word":"Flustered"},"615":{"definition":"ungrateful person","type":"","word":"Ingrate"},"616":{"definition":"concerned only with money","type":"","word":"Mercenary"},"617":{"definition":"minor weakness; trivial offence","type":"","word":"Peccadillo"},"618":{"definition":"person under protection of, or guided by another","type":"","word":"Prot\u00e9g\u00e9"},"619":{"definition":"inducing sleep","type":"","word":"Soporific"},"620":{"definition":"surface coating","type":"","word":"Veneer"},"621":{"definition":"clear; lucid; eloquent","type":"","word":"Articulate"},"622":{"definition":"customers","type":"","word":"Clientele"},"623":{"definition":"an inequality","type":"","word":"Disparity"},"624":{"definition":"unreliable; disreputable","type":"","word":"Fly-by-night"},"625":{"definition":"hostile","type":"","word":"Inimical"},"626":{"definition":"volatile; changeable","type":"","word":"Mercurial"},"627":{"definition":"person who insists on strict adherence to rules or narrow learning","type":"","word":"Pedant"},"628":{"definition":"procedure; code of behavior","type":"","word":"Protocol"},"629":{"definition":"spare; bare; meager","type":"","word":"Sparse"},"630":{"definition":"revere; worship","type":"","word":"Venerate"},"631":{"definition":"deception; trickery","type":"","word":"Artifice"},"632":{"definition":"come together; merge","type":"","word":"Coalesce"},"633":{"definition":"neutral; objective","type":"","word":"Dispassionate"},"634":{"definition":"concerned with argument or debate (esp. for legal evidence)","type":"","word":"Forensic"},"635":{"definition":"inherited; inborn","type":"","word":"Innate"},"636":{"definition":"come together","type":"","word":"Merge"},"637":{"definition":"common; mundane; banal","type":"","word":"Pedestrian"},"638":{"definition":"unsophisticated; narrow-minded","type":"","word":"Provincial"},"639":{"definition":"false","type":"","word":"Specious"},"640":{"definition":"minor; unimportant","type":"","word":"Venial"},"641":{"definition":"craftsman","type":"","word":"Artisan"},"642":{"definition":"pamper; fuss over; indulge","type":"","word":"Coddle"},"643":{"definition":"circulating; broadcasting; spreading (information)","type":"","word":"Disseminating"},"644":{"definition":"bravery","type":"","word":"Fortitude"},"645":{"definition":"harmless; inoffensive","type":"","word":"Innocuous"},"646":{"definition":"symbolically; figuratively","type":"","word":"Metaphorically"},"647":{"definition":"without equal","type":"","word":"Peerless"},"648":{"definition":"cautious; wise","type":"","word":"Prudent"},"649":{"definition":"spotted; freckled; dotted","type":"","word":"Speckled"},"650":{"definition":"truthfulness","type":"","word":"Veracity"},"651":{"definition":"without luxuries; severely simple","type":"","word":"Ascetic"},"652":{"definition":"force","type":"","word":"Coercion"},"653":{"definition":"active in daytime","type":"","word":"Diurnal"},"654":{"definition":"happening by chance","type":"","word":"Fortuitous"},"655":{"definition":"create; introduce something new","type":"","word":"Innovate"},"656":{"definition":"very careful; painstaking","type":"","word":"Meticulous"},"657":{"definition":"derogatory","type":"","word":"Pejorative"},"658":{"definition":"childish","type":"","word":"Puerile"},"659":{"definition":"not continuous; intermittent","type":"","word":"Sporadic"},"660":{"definition":"talkative; long-winded; rambling","type":"","word":"Verbose"},"661":{"definition":"thorough; diligent","type":"","word":"Assiduous"},"662":{"definition":"lucid; well argued","type":"","word":"Cogent"},"663":{"definition":"1. entertain; 2. distract; 3. cause a detour","type":"","word":"Divert"},"664":{"definition":"irritable; difficult to control","type":"","word":"Fractious"},"665":{"definition":"mysterious; impenetrable","type":"","word":"Inscrutable"},"666":{"definition":"courage; bravery; valor","type":"","word":"Mettle"},"667":{"definition":"transparently clear","type":"","word":"Pellucid"},"668":{"definition":"paying attention to small details","type":"","word":"Punctilious"},"669":{"definition":"false","type":"","word":"Spurious"},"670":{"definition":"using too many words","type":"","word":"Verbosity"},"671":{"definition":"to calm","type":"","word":"Assuage"},"672":{"definition":"think over something; ponder","type":"","word":"Cogitate"},"673":{"definition":"gentle and easily lead","type":"","word":"Docile"},"674":{"definition":"fake; false","type":"","word":"Fraudulent"},"675":{"definition":"unfeeling","type":"","word":"Insentient"},"676":{"definition":"environment","type":"","word":"Milieu"},"677":{"definition":"in a thoughtful mood; thinking deeply","type":"","word":"Pensive"},"678":{"definition":"steal","type":"","word":"Purloin"},"679":{"definition":"still; not moving","type":"","word":"Stagnant"},"680":{"definition":"dizziness","type":"","word":"Vertigo"},"681":{"definition":"perceptive; sharp-witted","type":"","word":"Astute"},"682":{"definition":"picture made from fragments of other pictures","type":"","word":"Collage"},"683":{"definition":"having stubbornly held opinions","type":"","word":"Dogmatic"},"684":{"definition":"not serious","type":"","word":"Frivolous"},"685":{"definition":"dull; bland; boring","type":"","word":"Insipid"},"686":{"definition":"swamp; muddy ground","type":"","word":"Mire"},"687":{"definition":"poverty","type":"","word":"Penury"},"688":{"definition":"cowardly","type":"","word":"Pusillanimous"},"689":{"definition":"dull; sober; serious","type":"","word":"Staid"},"690":{"definition":"not developed","type":"","word":"Vestigial"},"691":{"definition":"place of refuge or safety","type":"","word":"Asylum"},"692":{"definition":"arrange in order","type":"","word":"Collate"},"693":{"definition":"stupid person","type":"","word":"Dolt"},"694":{"definition":"economical; not wasting anything","type":"","word":"Frugal"},"695":{"definition":"to start; provoke","type":"","word":"Instigate"},"696":{"definition":"hater of the rest of mankind","type":"","word":"Misanthrope"},"697":{"definition":"observant","type":"","word":"Perceptive"},"698":{"definition":"compulsion to start fires","type":"","word":"Pyromania"},"699":{"definition":"section of a poem","type":"","word":"Stanza"},"700":{"definition":"small sketch","type":"","word":"Vignette"},"701":{"definition":"person who does not believe in God","type":"","word":"Atheist"},"702":{"definition":"local and informal (used of language)","type":"","word":"Colloquial"},"703":{"definition":"foolish old man","type":"","word":"Dotard"},"704":{"definition":"groove","type":"","word":"Furrow"},"705":{"definition":"troublemaker; person who entices others to do something","type":"","word":"Instigator"},"706":{"definition":"wrong name","type":"","word":"Misnomer"},"707":{"definition":"perceptive; insightful","type":"","word":"Percipient"},"708":{"definition":"drink down quickly","type":"","word":"Quaff"},"709":{"definition":"loyal; faithful; dependable","type":"","word":"Staunch"},"710":{"definition":"blackening someone's name","type":"","word":"Vilification"},"711":{"definition":"waste away from lack of use","type":"","word":"Atrophy"},"712":{"definition":"plotting and planning","type":"","word":"Collusion"},"713":{"definition":"speak slowly with words running together","type":"","word":"Drawl"},"714":{"definition":"hidden and secret","type":"","word":"Furtive"},"715":{"definition":"a rebel","type":"","word":"Insurgent"},"716":{"definition":"hater of women","type":"","word":"Misogynist"},"717":{"definition":"damnation","type":"","word":"Perdition"},"718":{"definition":"marsh; bog","type":"","word":"Quagmire"},"719":{"definition":"fixed image","type":"","word":"Stereotype"},"720":{"definition":"prove right; remove blame","type":"","word":"Vindicate"},"721":{"definition":"weaken","type":"","word":"Attenuate"},"722":{"definition":"take possession of","type":"","word":"Commandeer"},"723":{"definition":"nonsense","type":"","word":"Drivel"},"724":{"definition":"useless; hopeless","type":"","word":"Futile"},"725":{"definition":"never-ending","type":"","word":"Interminable"},"726":{"definition":"deliberately deceiving","type":"","word":"Misrepresentation"},"727":{"definition":"in a commanding manner","type":"","word":"Peremptory"},"728":{"definition":"picturesque","type":"","word":"Quaint"},"729":{"definition":"dockworker","type":"","word":"Stevedore"},"730":{"definition":"an accomplished musician","type":"","word":"Virtuoso"},"731":{"definition":"increase; make bigger","type":"","word":"Augment"},"732":{"definition":"self-satisfied; smug","type":"","word":"Complacent"},"733":{"definition":"dryly amusing","type":"","word":"Droll"},"734":{"definition":"ancient type of sailing ship","type":"","word":"Galleon"},"735":{"definition":"sporadic; irregular","type":"","word":"Intermittent"},"736":{"definition":"lessen; make less severe","type":"","word":"Mitigate"},"737":{"definition":"treachery","type":"","word":"Perfidy"},"738":{"definition":"dilemma; puzzle","type":"","word":"Quandary"},"739":{"definition":"suppress","type":"","word":"Stifle"},"740":{"definition":"dangerous; harmful","type":"","word":"Virulent"},"741":{"definition":"favorable; promising to turn out well","type":"","word":"Auspicious"},"742":{"definition":"easy to control; submissive","type":"","word":"Compliant"},"743":{"definition":"1. monotonous noise ","type":"","word":"Drone"},"744":{"definition":"; 2. to speak with no emotion ","type":"","word":"Gambol"},"745":{"definition":"; 3.male bee","type":"","word":"Intransigence"},"746":{"definition":"frolic; leap; bound","type":"","word":"Modicum"},"747":{"definition":"stubbornness","type":"","word":"Perfunctory"},"748":{"definition":"small amount","type":"","word":"Quarantine"},"749":{"definition":"superficial; cursory","type":"","word":"Stoic"},"750":{"definition":"isolation to prevent the spread of disease","type":"","word":"Vital"},"751":{"definition":"known for fortitude; indifferent to pleasure or pain","type":"","word":"Austere"},"752":{"definition":"essential; alive; important","type":"","word":"Concatenate"},"753":{"definition":"severely plain","type":"","word":"Dubious"},"754":{"definition":"link together","type":"","word":"Garble"},"755":{"definition":"doubtful","type":"","word":"Intransigent"},"756":{"definition":"distort; confuse; muddle","type":"","word":"Momentous"},"757":{"definition":"stubborn; unyielding","type":"","word":"Peripatetic"},"758":{"definition":"very important","type":"","word":"Quarry"},"759":{"definition":"nomadic; moving from place to place","type":"","word":"Stoke"},"760":{"definition":"1. something that is hunted; 2. mine for stone","type":"","word":"Vitriolic"},"761":{"definition":"add fuel to; strengthen","type":"","word":"Aversion"},"762":{"definition":"corrosive; strongly attacking","type":"","word":"Concatenation"},"763":{"definition":"a dislike of","type":"","word":"Dupe"},"764":{"definition":"linking into chains","type":"","word":"Garish"},"765":{"definition":"to fool someone","type":"","word":"Intrepid"},"766":{"definition":"gaudy","type":"","word":"Monotonous"},"767":{"definition":"brave","type":"","word":"Peripheral"},"768":{"definition":"dull; unvarying","type":"","word":"Querulous"},"769":{"definition":"on the edge; not important","type":"","word":"Stolid"},"770":{"definition":"always complaining","type":"","word":"Vivacity"},"771":{"definition":"impassive; dull; indifferent","type":"","word":"Balk"},"772":{"definition":"liveliness; animation","type":"","word":"Conciliate"},"773":{"definition":"hinder and prevent; hesitate over","type":"","word":"Dynamic"},"774":{"definition":"to bring together; end a dispute","type":"","word":"Garner"},"775":{"definition":"lively; vibrant; energetic","type":"","word":"Inveterate"},"776":{"definition":"gather; collect","type":"","word":"Moratorium"},"777":{"definition":"habitual","type":"","word":"Perjury"},"778":{"definition":"temporary prohibition or halt to activity","type":"","word":"Quirk"},"779":{"definition":"telling lies under oath","type":"","word":"Stratagem"},"780":{"definition":"oddity","type":"","word":"Vivify"},"781":{"definition":"plot; plan; trick","type":"","word":"Banal"},"782":{"definition":"enliven","type":"","word":"Concise"},"783":{"definition":"common; dull","type":"","word":"Ebullient"},"784":{"definition":"stated in few words","type":"","word":"Garrulous"},"785":{"definition":"very lively; cheerful; jovial; happy","type":"","word":"Invidious"},"786":{"definition":"talkative","type":"","word":"Moribund"},"787":{"definition":"arousing envy","type":"","word":"Pernicious"},"788":{"definition":"on the point of death","type":"","word":"Ramble"},"789":{"definition":"destructive; harmful","type":"","word":"Strident"},"790":{"definition":"wander aimlessly","type":"","word":"Vociferous"},"791":{"definition":"loud and harsh","type":"","word":"Banality"},"792":{"definition":"noisy; loud in speech","type":"","word":"Condescend"},"793":{"definition":"ordinariness; dullness","type":"","word":"Eccentric"},"794":{"definition":"talk down to","type":"","word":"Gaunt"},"795":{"definition":"unusual; quirky; odd","type":"","word":"Inviolable"},"796":{"definition":"emaciated; bony and angular","type":"","word":"Morose"},"797":{"definition":"cannot be invaded","type":"","word":"Persnickety"},"798":{"definition":"gloomy; bad tempered","type":"","word":"Ramifications"},"799":{"definition":"fastidious; fussy","type":"","word":"Stringent"},"800":{"definition":"branches; subdivisions of a complex system; outcomes","type":"","word":"Volatile"},"801":{"definition":"troublesome influence","type":"","word":"Bane"},"802":{"definition":"tacitly support; overlook","type":"","word":"Condone"},"803":{"definition":"taking things from different sources","type":"","word":"Eclectic"},"804":{"definition":"a category; type","type":"","word":"Genre"},"805":{"definition":"easily angered","type":"","word":"Irascible"},"806":{"definition":"ordinary; worldly","type":"","word":"Mundane"},"807":{"definition":"caused to continue","type":"","word":"Perpetuated"},"808":{"definition":"resentment; animosity; bad feeling","type":"","word":"Rancor"},"809":{"definition":"swagger; show off","type":"","word":"Strut"},"810":{"definition":"talkative","type":"","word":"Voluble"},"811":{"definition":"poet","type":"","word":"Bard"},"812":{"definition":"overlooking; disregarding; ignoring","type":"","word":"Condoning"},"813":{"definition":"building; structure; construction","type":"","word":"Edifice"},"814":{"definition":"relevant","type":"","word":"Germane"},"815":{"definition":"anger [","type":"","word":"Ire"},"816":{"definition":" = very angry]","type":"","word":"Munificent"},"817":{"definition":"generous; charitable","type":"","word":"Perpetuity"},"818":{"definition":"eternity","type":"","word":"Rant"},"819":{"definition":"use bombastic language","type":"","word":"Stupefying"},"820":{"definition":"astonishing; shocking; stunning into silence","type":"","word":"Voluminous"},"821":{"definition":"very large; spacious","type":"","word":"Bastion"},"822":{"definition":"fortress; stronghold","type":"","word":"Conflagration"},"823":{"definition":"big fire","type":"","word":"Efface"},"824":{"definition":"wipe out; remove all trace of","type":"","word":"Germinal"},"825":{"definition":"just growing; not developed; immature","type":"","word":"Irksome"},"826":{"definition":"annoying; infuriating","type":"","word":"Mutinous"},"827":{"definition":"very rebellious","type":"","word":"Personable"},"828":{"definition":"attractive","type":"","word":"Ratify"},"829":{"definition":"approve; consent","type":"","word":"Subpoena"},"830":{"definition":"summons to court","type":"","word":"Voracious"},"831":{"definition":"ravenous","type":"","word":"Befuddle"},"832":{"definition":"confuse","type":"","word":"Confound"},"833":{"definition":"confuse","type":"","word":"Effigy"},"834":{"definition":"a model of a person","type":"","word":"Gibbering"},"835":{"definition":"making meaningless noises","type":"","word":"Ironic"},"836":{"definition":"satiric; unexpected","type":"","word":"Myriad"},"837":{"definition":"in large numbers","type":"","word":"Perspicacious"},"838":{"definition":"insightful; sharp; wise","type":"","word":"Raucous"},"839":{"definition":"rough and unpleasant (of sounds)","type":"","word":"Substantiate"},"840":{"definition":"give supporting evidence","type":"","word":"Waive"},"841":{"definition":"surrender; give up","type":"","word":"Begrudge"},"842":{"definition":"resent","type":"","word":"Congeal"},"843":{"definition":"to solidify","type":"","word":"Effusive"},"844":{"definition":"gushing; demonstrative","type":"","word":"Glacial"},"845":{"definition":"hostile; unfriendly; cold; icy","type":"","word":"Irrational"},"846":{"definition":"unreasonable; absurd","type":"","word":"Navigable"},"847":{"definition":"suitable for sailing","type":"","word":"Perspicacity"},"848":{"definition":"insight","type":"","word":"Raze"},"849":{"definition":"destroy; demolish; tear down","type":"","word":"Subterfuge"},"850":{"definition":"a trick","type":"","word":"Wane"},"851":{"definition":"grow less","type":"","word":"Beguile"},"852":{"definition":"mislead; lure","type":"","word":"Congenital"},"853":{"definition":"present from birth","type":"","word":"Egalitarianism"},"854":{"definition":"belief in equality","type":"","word":"Goad"},"855":{"definition":"prod; urge","type":"","word":"Irreproachable"},"856":{"definition":"cannot be criticized; perfect","type":"","word":"Nebulous"},"857":{"definition":"vague","type":"","word":"Pertinent"},"858":{"definition":"relevant","type":"","word":"Rebuttal"},"859":{"definition":"denial","type":"","word":"Subtle"},"860":{"definition":"not obvious","type":"","word":"Wary"},"861":{"definition":"hesitant; cautious","type":"","word":"Belabor"},"862":{"definition":"explain in unnecessary detail","type":"","word":"Connoisseur"},"863":{"definition":"person with refined taste and good judgment","type":"","word":"Egregious"},"864":{"definition":"outstandingly, obviously bad","type":"","word":"Grate "},"865":{"definition":"1. to annoy; aggravate; vex; 2. shred","type":"","word":"Irrevocable"},"866":{"definition":"cannot be cancelled; unchangeable","type":"","word":"Nefarious"},"867":{"definition":"wicked; immoral; disreputable","type":"","word":"Peruse"},"868":{"definition":"read carefully","type":"","word":"Recant"},"869":{"definition":"disclaim; retract statement","type":"","word":"Subversive"},"870":{"definition":"rebellious; revolutionary","type":"","word":"Wax"},"871":{"definition":"to increase; to grow","type":"","word":"Beleaguer"},"872":{"definition":"besiege; attack","type":"","word":"Consecrate"},"873":{"definition":"dedicate","type":"","word":"Egress"},"874":{"definition":"exit","type":"","word":"Gratis"},"875":{"definition":"free of charge; without payment","type":"","word":"Itinerant"},"876":{"definition":"nomadic; wandering from place to place","type":"","word":"Negate"},"877":{"definition":"cancel; deny","type":"","word":"Pervasive"},"878":{"definition":"spreading everywhere","type":"","word":"Recapitulate"},"879":{"definition":"summarize","type":"","word":"Succinct"},"880":{"definition":"concise","type":"","word":"Waylay"},"881":{"definition":"accost; stop; approach; hinder","type":"","word":"Belie"},"882":{"definition":"contradict","type":"","word":"Consensus"},"883":{"definition":"general agreement","type":"","word":"Eloquent"},"884":{"definition":"fluent and persuasive in speech","type":"","word":"Gratuitous"},"885":{"definition":"unwarranted","type":"","word":"Jaded"},"886":{"definition":"tired; bored; worn out","type":"","word":"Negligence"},"887":{"definition":"carelessness","type":"","word":"Petrify"},"888":{"definition":"1. terrify; 2. turn to stone","type":"","word":"Receptacle"},"889":{"definition":"container; vessel; holder","type":"","word":"Suffragist"},"890":{"definition":"someone who campaigns for voting rights","type":"","word":"Weighty"},"891":{"definition":"serious","type":"","word":"Belittle"},"892":{"definition":"to demean","type":"","word":"Conspicuous"},"893":{"definition":"easily seen; prominent","type":"","word":"Elucidate"},"894":{"definition":"make clear","type":"","word":"Gravity"},"895":{"definition":"seriousness","type":"","word":"Jargon"},"896":{"definition":"specialized language used by experts","type":"","word":"Neologism"},"897":{"definition":"newly coined word","type":"","word":"Petulant"},"898":{"definition":"sulky; peevish","type":"","word":"Recluse"},"899":{"definition":"someone who cuts himself off from life","type":"","word":"Supercilious"},"900":{"definition":"proud and haughty","type":"","word":"Whelp"},"901":{"definition":"war-like; aggressive","type":"","word":"Bellicose"},"902":{"definition":"complete; total; supremely good","type":"","word":"Consummate"},"903":{"definition":"hard to pin down","type":"","word":"Elusive"},"904":{"definition":"extroverted; sociable; outgoing","type":"","word":"Gregarious"},"905":{"definition":"cynical; pessimistic","type":"","word":"Jaundiced"},"906":{"definition":"annoy","type":"","word":"Nettle"},"907":{"definition":"an event or happening (plural: phenomena)","type":"","word":"Phenomenon"},"908":{"definition":"get better after illness","type":"","word":"Recuperate"},"909":{"definition":"extremely good; the best","type":"","word":"Superlative"},"910":{"definition":"sharpen","type":"","word":"Whet"},"911":{"definition":"aggressive; ready to fight","type":"","word":"Belligerent"},"912":{"definition":"living or happening at the same time","type":"","word":"Contemporary"},"913":{"definition":"very thin; withered","type":"","word":"Emaciated"},"914":{"definition":"coarse; granular","type":"","word":"Gritty"},"915":{"definition":"short pleasure trip","type":"","word":"Jaunt"},"916":{"definition":"miserly; stingy","type":"","word":"Niggardly"},"917":{"definition":"charity; love of mankind","type":"","word":"Philanthropy"},"918":{"definition":"formalities; paperwork; official procedure","type":"","word":"Red tape"},"919":{"definition":"grumpy; rude","type":"","word":"Surly"},"920":{"definition":"capricious; changeable","type":"","word":"Whimsical"},"921":{"definition":"complain about","type":"","word":"Bemoan"},"922":{"definition":"sorry","type":"","word":"Contrite"},"923":{"definition":"set free","type":"","word":"Emancipate"},"924":{"definition":"sudden loud laughter","type":"","word":"Guffaw"},"925":{"definition":"put at risk; endanger","type":"","word":"Jeopardize"},"926":{"definition":"wandering from place to place","type":"","word":"Nomadic"},"927":{"definition":"uncultured person","type":"","word":"Philistine"},"928":{"definition":"smelling of; giving off odors","type":"","word":"Redolent"},"929":{"definition":"secret; sneaky; stealthy","type":"","word":"Surreptitious"},"930":{"definition":"stubborn","type":"","word":"Willful"},"931":{"definition":"kindly","type":"","word":"Benevolent"},"932":{"definition":"sorrow and repentance","type":"","word":"Contrition"},"933":{"definition":"defraud; steal","type":"","word":"Embezzle"},"934":{"definition":"cunning; craftiness","type":"","word":"Guile"},"935":{"definition":"extremely patriotic; nationalistic","type":"","word":"Jingoistic"},"936":{"definition":"an appearance of indifference; calm and composed","type":"","word":"Nonchalance"},"937":{"definition":"calm; imperturbable","type":"","word":"Phlegmatic"},"938":{"definition":"put right something that was wrong","type":"","word":"Redress"},"939":{"definition":"secretly; furtively; stealthily","type":"","word":"Surreptitiously"},"940":{"definition":"cunning","type":"","word":"Wily"},"941":{"definition":"kindly; harmless","type":"","word":"Benign"},"942":{"definition":"stubborn","type":"","word":"Contumacious"},"943":{"definition":"involve in hostility or argument","type":"","word":"Embroil"},"944":{"definition":"frank; straightforward; honest","type":"","word":"Guileless"},"945":{"definition":"in a joking manner","type":"","word":"Jocular"},"946":{"definition":"having no special features; dull and ordinary","type":"","word":"Nondescript"},"947":{"definition":"plunder","type":"","word":"Pillage"},"948":{"definition":"unnecessary; superfluous","type":"","word":"Redundant"},"949":{"definition":"vulnerable","type":"","word":"Susceptible"},"950":{"definition":"flimsy; frail; delicate","type":"","word":"Wispy"},"951":{"definition":"compassion; gentleness; fondness","type":"","word":"Benignity"},"952":{"definition":"a bruise","type":"","word":"Contusion"},"953":{"definition":"come out; appear","type":"","word":"Emerge"},"954":{"definition":"unwariness; trustfulness; being easily fooled","type":"","word":"Gullibility"},"955":{"definition":"gaiety; happiness","type":"","word":"Jollity"},"956":{"definition":"a person of no importance; not famous","type":"","word":"Nonentity"},"957":{"definition":"topmost point","type":"","word":"Pinnacle"},"958":{"definition":"public vote","type":"","word":"Referendum"},"959":{"definition":"doubtful","type":"","word":"Suspect"},"960":{"definition":"melancholy; pensive; expressing a longing for","type":"","word":"Wistful"},"961":{"definition":"leave something in one's will to be given after one's death","type":"","word":"Bequeath"},"962":{"definition":"a puzzle","type":"","word":"Conundrum"},"963":{"definition":"to imitate something admired","type":"","word":"Emulate"},"964":{"definition":"easily fooled","type":"","word":"Gullible"},"965":{"definition":"ecstatic; delighted; rejoicing","type":"","word":"Jubilant"},"966":{"definition":"longing for the past","type":"","word":"Nostalgia"},"967":{"definition":"very religious","type":"","word":"Pious"},"968":{"definition":"disprove","type":"","word":"Refute"},"969":{"definition":"lover of luxury","type":"","word":"Sybarite"},"970":{"definition":"crazy; wacky","type":"","word":"Zany"},"971":{"definition":"scold; criticize","type":"","word":"Berate"},"972":{"definition":"usual; customary; common","type":"","word":"Conventional"},"973":{"definition":"give support or approval to","type":"","word":"Endorse"},"974":{"definition":"concerned with the sense of taste","type":"","word":"Gustatory"},"975":{"definition":"correct in judgment; wise","type":"","word":"Judicious"},"976":{"definition":"infamy; known for wrong doing","type":"","word":"Notoriety"},"977":{"definition":"of central importance","type":"","word":"Pivotal"},"978":{"definition":"entertain","type":"","word":"Regale"},"979":{"definition":"bootlicker; flatterer","type":"","word":"Sycophant"},"980":{"definition":"enthusiasm","type":"","word":"Zeal"},"981":{"definition":"type of cap","type":"","word":"Beret"},"982":{"definition":"fat","type":"","word":"Corpulent"},"983":{"definition":"staying power; patience; stamina","type":"","word":"Endurance"},"984":{"definition":"common and over-used","type":"","word":"Hackneyed"},"985":{"definition":"science or study of law","type":"","word":"Jurisprudence"},"986":{"definition":"new; unusual","type":"","word":"Novel"},"987":{"definition":"pacify; soothe; calm","type":"","word":"Placate"},"988":{"definition":"dismiss to a lower position","type":"","word":"Relegate"},"989":{"definition":"quiet; saying little","type":"","word":"Taciturn"},"990":{"definition":"fanatic","type":"","word":"Zealot"},"991":{"definition":"behaving like a beast; brutal","type":"","word":"Bestial"},"992":{"definition":"highly folded","type":"","word":"Corrugated"},"993":{"definition":"lasting","type":"","word":"Enduring"},"994":{"definition":"worshipped; consecrated","type":"","word":"Hallowed"},"995":{"definition":"place next to","type":"","word":"Juxtapose"},"996":{"definition":"a beginner; tyro","type":"","word":"Novice"},"997":{"definition":"harmless medicine with no effect; dummy medicine","type":"","word":"Placebo"},"998":{"definition":"regret; sorrow; contrition","type":"","word":"Remorse"},"999":{"definition":"concerned with the sense of touch","type":"","word":"Tactile"},"1000":{"definition":"summit","type":"","word":"Zenith"}}}